{"dict_name": "pokemon", "epoch": 200, "height": 24, "list": [{"i": 18, "j": 16, "ori": 0, "word": "ヤトウモリ"}, {"i": 19, "j": 13, "ori": 1, "word": "ゴビット"}, {"i": 22, "j": 12, "ori": 1, "word": "オドリドリ"}, {"i": 18, "j": 16, "ori": 1, "word": "ヤンチャム"}, {"i": 14, "j": 17, "ori": 0, "word": "マンタイン"}, {"i": 16, "j": 14, "ori": 0, "word": "サクラビス"}, {"i": 14, "j": 17, "ori": 1, "word": "マンムー"}, {"i": 10, "j": 18, "ori": 0, "word": "クマシュン"}, {"i": 12, "j": 18, "ori": 1, "word": "シャワーズ"}, {"i": 9, "j": 21, "ori": 0, "word": "エレブー"}, {"i": 17, "j": 10, "ori": 1, "word": "トゲチック"}, {"i": 17, "j": 10, "ori": 0, "word": "トゲデマル"}, {"i": 21, "j": 7, "ori": 1, "word": "ワルビル"}, {"i": 17, "j": 8, "ori": 0, "word": "ルチャブル"}, {"i": 17, "j": 5, "ori": 1, "word": "ミミロル"}, {"i": 19, "j": 4, "ori": 1, "word": "ゴローニャ"}, {"i": 14, "j": 5, "ori": 0, "word": "シェイミ"}, {"i": 16, "j": 1, "ori": 1, "word": "コフーライ"}, {"i": 12, "j": 3, "ori": 0, "word": "ホエルオー"}, {"i": 14, "j": 1, "ori": 0, "word": "キノココ"}, {"i": 9, "j": 19, "ori": 1, "word": "フラエッテ"}, {"i": 12, "j": 3, "ori": 1, "word": "ホルード"}, {"i": 12, "j": 22, "ori": 0, "word": "ズバット"}, {"i": 5, "j": 20, "ori": 0, "word": "バイバニラ"}, {"i": 20, "j": 12, "ori": 0, "word": "フィオネ"}, {"i": 7, "j": 18, "ori": 1, "word": "バンバドロ"}, {"i": 4, "j": 18, "ori": 0, "word": "メラルバ"}, {"i": 4, "j": 16, "ori": 1, "word": "スバメ"}, {"i": 6, "j": 14, "ori": 1, "word": "モウカザル"}, {"i": 1, "j": 16, "ori": 0, "word": "ヒンバス"}, {"i": 3, "j": 14, "ori": 0, "word": "ヤルキモノ"}, {"i": 4, "j": 10, "ori": 1, "word": "モロバレル"}, {"i": 1, "j": 12, "ori": 1, "word": "カプ・レヒレ"}, {"i": 6, "j": 16, "ori": 0, "word": "カメテテ"}, {"i": 3, "j": 11, "ori": 0, "word": "ゴローン"}, {"i": 6, "j": 8, "ori": 1, "word": "ジーランス"}, {"i": 3, "j": 8, "ori": 0, "word": "カエンジシ"}, {"i": 0, "j": 12, "ori": 0, "word": "ポカブ"}, {"i": 7, "j": 6, "ori": 1, "word": "ヨワシ"}, {"i": 19, "j": 5, "ori": 0, "word": "ロコン"}, {"i": 10, "j": 4, "ori": 0, "word": "リオル"}, {"i": 10, "j": 2, "ori": 1, "word": "アブリー"}, {"i": 8, "j": 5, "ori": 0, "word": "ブルー"}, {"i": 9, "j": 2, "ori": 0, "word": "ギアル"}, {"i": 20, "j": 16, "ori": 1, "word": "ウパー"}, {"i": 16, "j": 16, "ori": 1, "word": "メタグロス"}, {"i": 11, "j": 0, "ori": 1, "word": "コイル"}, {"i": 10, "j": 0, "ori": 0, "word": "ココドラ"}, {"i": 5, "j": 5, "ori": 1, "word": "ピジョン"}, {"i": 14, "j": 3, "ori": 1, "word": "ルクシオ"}, {"i": 23, "j": 10, "ori": 1, "word": "マネネ"}, {"i": 3, "j": 5, "ori": 0, "word": "ピッピ"}, {"i": 3, "j": 5, "ori": 1, "word": "ピィ"}, {"i": 8, "j": 3, "ori": 1, "word": "クラブ"}, {"i": 0, "j": 10, "ori": 1, "word": "ポッポ"}, {"i": 5, "j": 3, "ori": 0, "word": "ピンプク"}, {"i": 6, "j": 2, "ori": 1, "word": "サンド"}], "mask": [[false, false, false, false, false, false, false, false, false, true, true, true, true, true, true, false, false, false, false, false, false, false, false, false], [false, false, false, false, false, false, true, true, true, true, true, true, true, true, true, true, true, true, false, false, false, false, false, false], [false, false, false, false, false, true, true, true, true, true, true, true, true, true, true, true, true, true, true, false, false, false, false, false], [false, false, false, false, true, true, true, true, true, true, true, true, true, true, true, true, true, true, true, true, false, false, false, false], [false, false, false, true, true, true, true, true, true, true, true, true, true, true, true, true, true, true, true, true, true, false, false, false], [false, false, true, true, true, true, true, true, true, true, true, true, true, true, true, true, true, true, true, true, true, true, false, false], [false, true, true, true, true, true, true, true, true, true, true, true, true, true, true, true, true, true, true, true, true, true, true, false], [false, true, true, true, true, true, true, true, true, true, false, false, false, false, true, true, true, true, true, true, true, true, true, false], [false, true, true, true, true, true, true, true, false, false, false, false, false, false, false, false, true, true, true, true, true, true, true, false], [true, true, true, true, true, true, true, true, false, false, false, false, false, false, false, false, true, true, true, true, true, true, true, true], [true, true, true, true, true, true, true, false, false, false, false, false, false, false, false, false, false, true, true, true, true, true, true, true], [true, true, true, true, true, true, true, false, false, false, false, false, false, false, false, false, false, true, true, true, true, true, true, true], [true, true, true, true, true, true, true, false, false, false, false, false, false, false, false, false, false, true, true, true, true, true, true, true], [true, true, true, true, true, true, true, false, false, false, false, false, false, false, false, false, false, true, true, true, true, true, true, true], [true, true, true, true, true, true, true, true, false, false, false, false, false, false, false, false, true, true, true, true, true, true, true, true], [false, true, true, true, true, true, true, true, false, false, false, false, false, false, false, false, true, true, true, true, true, true, true, false], [false, true, true, true, true, true, true, true, true, true, false, false, false, false, true, true, true, true, true, true, true, true, true, false], [false, true, true, true, true, true, true, true, true, true, true, true, true, true, true, true, true, true, true, true, true, true, true, false], [false, false, true, true, true, true, true, true, true, true, true, true, true, true, true, true, true, true, true, true, true, true, false, false], [false, false, false, true, true, true, true, true, true, true, true, true, true, true, true, true, true, true, true, true, true, false, false, false], [false, false, false, false, true, true, true, true, true, true, true, true, true, true, true, true, true, true, true, true, false, false, false, false], [false, false, false, false, false, true, true, true, true, true, true, true, true, true, true, true, true, true, true, false, false, false, false, false], [false, false, false, false, false, false, true, true, true, true, true, true, true, true, true, true, true, true, false, false, false, false, false, false], [false, false, false, false, false, false, false, false, false, true, true, true, true, true, true, false, false, false, false, false, false, false, false, false]], "name": "Donut Puzzle", "nwords": 57, "seed": 5, "width": 24}