{"dict_name": "pokemon", "epoch": 5, "height": 15, "list": [{"i": 10, "j": 9, "ori": 0, "word": "アマージョ"}, {"i": 11, "j": 8, "ori": 1, "word": "クマシュン"}, {"i": 7, "j": 12, "ori": 0, "word": "アーゴヨン"}, {"i": 8, "j": 11, "ori": 1, "word": "イーブイ"}, {"i": 5, "j": 14, "ori": 0, "word": "オーダイル"}, {"i": 5, "j": 11, "ori": 1, "word": "バスラオ"}, {"i": 2, "j": 12, "ori": 0, "word": "パチリス"}, {"i": 3, "j": 9, "ori": 1, "word": "ウソハチ"}, {"i": 3, "j": 9, "ori": 0, "word": "ウパー"}, {"i": 13, "j": 7, "ori": 1, "word": "ルージュラ"}, {"i": 4, "j": 5, "ori": 1, "word": "マスキッパ"}, {"i": 0, "j": 5, "ori": 0, "word": "ポッチャマ"}, {"i": 2, "j": 3, "ori": 1, "word": "ピカチュウ"}, {"i": 2, "j": 3, "ori": 0, "word": "ピンプク"}, {"i": 0, "j": 5, "ori": 1, "word": "ポカブ"}, {"i": 12, "j": 7, "ori": 0, "word": "ブルー"}, {"i": 12, "j": 5, "ori": 1, "word": "クラブ"}, {"i": 9, "j": 5, "ori": 0, "word": "ナゾノクサ"}, {"i": 5, "j": 0, "ori": 1, "word": "ドータクン"}, {"i": 4, "j": 1, "ori": 0, "word": "ブースター"}, {"i": 11, "j": 2, "ori": 1, "word": "ソーナノ"}, {"i": 8, "j": 3, "ori": 0, "word": "スピアー"}, {"i": 10, "j": 5, "ori": 1, "word": "ゾロア"}, {"i": 8, "j": 0, "ori": 1, "word": "コータス"}], "mask": [[true, true, true, true, true, false, false, false, false, false, true, true, true, true, true], [true, true, true, false, false, false, false, false, false, false, false, false, true, true, true], [true, true, false, false, false, false, false, false, false, false, false, false, false, true, true], [true, false, false, false, false, false, false, false, false, false, false, false, false, false, true], [true, false, false, false, false, false, false, false, false, false, false, false, false, false, true], [false, false, false, false, false, false, true, true, true, false, false, false, false, false, false], [false, false, false, false, false, true, true, true, true, true, false, false, false, false, false], [false, false, false, false, false, true, true, true, true, true, false, false, false, false, false], [false, false, false, false, false, true, true, true, true, true, false, false, false, false, false], [false, false, false, false, false, false, true, true, true, false, false, false, false, false, false], [true, false, false, false, false, false, false, false, false, false, false, false, false, false, true], [true, false, false, false, false, false, false, false, false, false, false, false, false, false, true], [true, true, false, false, false, false, false, false, false, false, false, false, false, true, true], [true, true, true, false, false, false, false, false, false, false, false, false, true, true, true], [true, true, true, true, true, false, false, false, false, false, true, true, true, true, true]], "name": "Pyzzle", "nwords": 24, "seed": 5, "width": 15}